<instance version="4" description="" template="ebps">
	<list name="extensions">
		<template_reference name="exts" value="ebpextensions\ability_ext" List.ItemID="-1790907575" List.ParentItemID="-1790907575">
			<list name="abilities" overrideParent="True">
				<instance_reference name="ability" value="abilities\modal_abilities\core\fireship_target" List.ItemID="819982236" />
			</list>
		</template_reference>
		<template_reference name="exts" value="ebpextensions\tier_ext" List.ItemID="-1332237399" List.ParentItemID="-1332237399">
			<list name="tier_group_list">
				<list name="tier_group" List.ItemID="-996648013" List.ParentItemID="-996648013">
					<group name="tier" List.ItemID="-696193104" List.ParentItemID="-696193104">
						<instance_reference name="attachments" value="attachments\attachment_lists\civilizations\hre\units\tier3_naval_fireship_hre" overrideParent="True" />
					</group>
				</list>
			</list>
		</template_reference>
		<template_reference name="exts" value="ebpextensions\interactive_object_ext" List.ItemID="-602433227" List.ListAction="Append">
			<list name="type_list" overrideParent="True">
				<group name="type" List.ItemID="-753001456">
					<enum name="interaction_type" value="inspire_hre" overrideParent="True" />
					<int name="prefer_number" value="1" overrideParent="True" />
					<int name="max_number" value="1" overrideParent="True" />
					<enum name="interaction_target_type" value="entity" />
					<template_reference name="node_list_option" value="options\none" overrideParent="True">
					</template_reference>
					<bool name="block_pathing_when_interacted" value="False" />
				</group>
			</list>
		</template_reference>
	</list>
	<uniqueid name="pbgid" value="193092" />
	<instance_reference name="parent_pbg" value="ebps\races\core\units\unit_naval_fireship_3" mod="754eeb87b7624e0a8a9a710767df6171" />
</instance>